imgtec.codescape-8.6.5a1513346799-py2.7-nspkg.pth
imgtec/codescape/CSDQer.jar
imgtec/codescape/DAscript.py
imgtec/codescape/DAtinyscript.py
imgtec/codescape/_DAscript.so
imgtec/codescape/__init__.py
imgtec/codescape/acquirer.py
imgtec/codescape/acquirer_reservations.py
imgtec/codescape/acquirer_server.py
imgtec/codescape/acquirer_targets.py
imgtec/codescape/breakpoint.py
imgtec/codescape/callstack.py
imgtec/codescape/channel.py
imgtec/codescape/core.py
imgtec/codescape/da.py
imgtec/codescape/da_config.py
imgtec/codescape/da_exception.py
imgtec/codescape/da_symbol.py
imgtec/codescape/da_thread.py
imgtec/codescape/da_types.py
imgtec/codescape/disassembly.py
imgtec/codescape/dtm.py
imgtec/codescape/fileserver.py
imgtec/codescape/help.py
imgtec/codescape/hwdefs.py
imgtec/codescape/img_xml.py
imgtec/codescape/memory.py
imgtec/codescape/overlays.py
imgtec/codescape/probe.py
imgtec/codescape/probe_config.py
imgtec/codescape/probe_finder.py
imgtec/codescape/probe_identifier.py
imgtec/codescape/program_file.py
imgtec/codescape/register_templates.py
imgtec/codescape/service_discovery.py
imgtec/codescape/sim_server.py
imgtec/codescape/soc.py
imgtec/codescape/source.py
imgtec/codescape/tiny.py
imgtec/codescape/virtual_probe
imgtec/console/__init__.py
imgtec/console/__main__.py
imgtec/console/assembler.py
imgtec/console/breakpoints.py
imgtec/console/cache.py
imgtec/console/calibrate_pdtrace.py
imgtec/console/cfg.py
imgtec/console/commands.py
imgtec/console/consoletest.py
imgtec/console/dbu_monitor.py
imgtec/console/dbudriver.py
imgtec/console/debug_monitor.py
imgtec/console/examples.py
imgtec/console/firmware.py
imgtec/console/flash.py
imgtec/console/generic_device.py
imgtec/console/hexfile.py
imgtec/console/iftrace.py
imgtec/console/main.py
imgtec/console/memory.py
imgtec/console/mt.py
imgtec/console/pc_sample.py
imgtec/console/pdtrace.py
imgtec/console/perfcount.py
imgtec/console/program_file.py
imgtec.codescape-8.6.5a1513346799.dist-info/DESCRIPTION.rst
imgtec.codescape-8.6.5a1513346799.dist-info/LICENSE.txt
imgtec.codescape-8.6.5a1513346799.dist-info/METADATA
imgtec.codescape-8.6.5a1513346799.dist-info/RECORD
imgtec.codescape-8.6.5a1513346799.dist-info/WHEEL
imgtec.codescape-8.6.5a1513346799.dist-info/entry_points.txt
imgtec.codescape-8.6.5a1513346799.dist-info/metadata.json
imgtec.codescape-8.6.5a1513346799.dist-info/namespace_packages.txt
imgtec.codescape-8.6.5a1513346799.dist-info/top_level.txt
