Metadata-Version: 2.0
Name: imgtec.codescape
Version: 8.6.5a1513346799
Summary: Codescape scripting interface
Home-page: http://www.mips.com/
Author: MIPS Tech LLC
Author-email: codescape-support@mips.com
License: LICENSE.txt
Platform: UNKNOWN
Classifier: Programming Language :: Python :: 2.7
Classifier: License :: Other/Proprietary License
Classifier: Intended Audience :: Developers
Classifier: Topic :: Software Development :: Debuggers
Classifier: Topic :: Software Development :: Disassemblers
Classifier: Topic :: Software Development :: Embedded Systems
Requires-Dist: certifi
Requires-Dist: jinja2
